crewai_olostep/__init__.py
crewai_olostep/tools.py
crewai_olostep-0.1.1.dist-info/METADATA
crewai_olostep-0.1.1.dist-info/WHEEL
crewai_olostep-0.1.1.dist-info/top_level.txt
crewai_olostep-0.1.1.dist-info/RECORD
