Metadata-Version: 2.4
Name: crewai-olostep
Version: 0.1.1
Summary: CrewAI tools for web scraping and research using Olostep API
Author-email: Olostep <info@olostep.com>
License: MIT
Project-URL: Homepage, https://olostep.com
Project-URL: Documentation, https://docs.olostep.com/integrations/crewai
Project-URL: Repository, https://github.com/olostep/olostep-tools
Project-URL: Issues, https://github.com/olostep/olostep-tools/issues
Keywords: crewai,olostep,web-scraping,ai-agents,multi-agent,automation,research
Classifier: Development Status :: 4 - Beta
Classifier: Intended Audience :: Developers
Classifier: License :: OSI Approved :: MIT License
Classifier: Programming Language :: Python :: 3
Classifier: Programming Language :: Python :: 3.10
Classifier: Programming Language :: Python :: 3.11
Classifier: Programming Language :: Python :: 3.12
Classifier: Topic :: Software Development :: Libraries :: Python Modules
Classifier: Topic :: Internet :: WWW/HTTP :: Indexing/Search
Requires-Python: >=3.10
Requires-Dist: crewai>=0.70.0
Requires-Dist: olostep>=0.9.0
Requires-Dist: pydantic>=2.0.0
Requires-Dist: requests>=2.28.0
Provides-Extra: dev
Requires-Dist: pytest>=7.0.0; extra == "dev"
Requires-Dist: pytest-asyncio>=0.21.0; extra == "dev"
Requires-Dist: black>=23.0.0; extra == "dev"
Requires-Dist: ruff>=0.1.0; extra == "dev"
